mh_structlog/__init__.py
mh_structlog/aws.py
mh_structlog/config.py
mh_structlog/django.py
mh_structlog/processors.py
mh_structlog/sentry.py
mh_structlog/utils.py
mh_structlog-0.0.46.dist-info/WHEEL
mh_structlog-0.0.46.dist-info/METADATA
mh_structlog-0.0.46.dist-info/RECORD
