Metadata-Version: 2.3
Name: mh_structlog
Version: 0.0.46
Summary: Some Structlog configuration and wrappers to easily use structlog.
Author: Mathieu Hinderyckx
Author-email: Mathieu Hinderyckx <mathieu.hinderyckx@gmail.com>
Classifier: Programming Language :: Python :: 3
Classifier: License :: OSI Approved :: MIT License
Classifier: Operating System :: OS Independent
Requires-Dist: orjson>=3.11.5
Requires-Dist: rich>=14.2.0
Requires-Dist: structlog>=25.5.0
Requires-Dist: aws-lambda-powertools>=3.23.0 ; extra == 'aws'
Requires-Dist: django>=5.0 ; extra == 'django'
Requires-Dist: structlog-sentry>=2.2.1 ; extra == 'sentry'
Requires-Python: >=3.10
Provides-Extra: aws
Provides-Extra: django
Provides-Extra: sentry
